pyCDxAnalysis/CDx.py
pyCDxAnalysis/__init__.py
pyCDxAnalysis/gene_patterns.py
pyCDxAnalysis/pypeta2.py
pyCDxAnalysis-0.0.30.dist-info/LICENSE
pyCDxAnalysis-0.0.30.dist-info/METADATA
pyCDxAnalysis-0.0.30.dist-info/WHEEL
pyCDxAnalysis-0.0.30.dist-info/top_level.txt
pyCDxAnalysis-0.0.30.dist-info/RECORD
