Metadata-Version: 2.1
Name: pyCDxAnalysis
Version: 0.0.30
Summary: Integrative tools to anlysis companian diagnosis gene data set.
Home-page: https://github.com/JaylanLiu/pyCDxAnalysis
Author: JaylanLiu
Author-email: liujilong@genomics.cn
License: UNKNOWN
Platform: UNKNOWN
Classifier: Development Status :: 3 - Alpha
Classifier: Intended Audience :: Developers
Classifier: Topic :: Scientific/Engineering :: Bio-Informatics
Classifier: License :: OSI Approved :: MIT License
Classifier: Programming Language :: Python :: 3.5
Classifier: Programming Language :: Python :: 3.6
Classifier: Programming Language :: Python :: 3.7
License-File: LICENSE
Requires-Dist: pandas (>1.0)
Requires-Dist: numpy
Requires-Dist: tableone
Requires-Dist: pyoncoprint
Requires-Dist: pypeta (>=0.6.8)
